mozdebug/__init__.py
mozdebug/mozdebug.py
mozdebug-0.4.0.dist-info/METADATA
mozdebug-0.4.0.dist-info/WHEEL
mozdebug-0.4.0.dist-info/top_level.txt
mozdebug-0.4.0.dist-info/RECORD
